Workbook
Name UK: 'United Kingdom'!$B$2

Sheet Master Excel with XelPlus
C4: Join 400,000+ professionals who've automated their reporting and become the go-to person on their team
C6: → Turn a 3-day reporting job into a couple of hours → Build dashboards that make your boss's jaw drop → Clean messy data in minutes. Not hours of copy-paste frustration | D6: 1 method: Right Click on the arrows (bottom left) to check the spreadsheet you want to modify.

Sheet Summary
D2: Global Subsidiaries Overview
D3: Consolidated Performance Dashboard
K4: NOTE: On Images, Eg.On UK image right click -> HyperLink -> Place in This Document -> Select United Kingdom (Spreadsheet). Repeat this process for other countries. | R4: TOTAL Revenue | S4: TOTAL Headcount
D5: PERFORMANCE BY REGION | R5: =SUM(E7:E15) -> 10245746 | S5: =SUM(F7:F15) -> 1840
D6: Country | E6: Annual Revenue | F6: Headcount | G6: YoY Growth | H6: Status
D7: United Kingdom | E7: ='United Kingdom'!D11 -> 1106993 | F7: ='United Kingdom'!C19 -> 160 | G7: 0.047242047 | H7: ●
D8: USA | E8: ='United States'!D11 -> 2570627 | F8: ='United States'!C19 -> 450 | G8: 0.078680987 | H8: ●
D9: Canada | E9: =Canada!D11 -> 787810 | F9: =Canada!C19 -> 120 | G9: 0.056934582 | H9: ●
D10: Germany | E10: =Germany!D11 -> 1239152 | F10: =Germany!C19 -> 180 | G10: 0.023936715 | H10: ●
D11: Austria | E11: =Austria!D11 -> 403493 | F11: =Austria!C19 -> 65 | G11: 0.023572104 | H11: ●
D12: France | E12: =France!D11 -> 981691 | F12: =France!C19 -> 140 | G12: -0.049946253 | H12: ●
D13: India | E13: =India!D11 -> 619513 | F13: =India!C19 -> 280 | G13: 0.11794454 | H13: ●
D14: China | E14: =China!D11 -> 1830941 | F14: =China!C19 -> 350 | G14: 0.091141806 | H14: ●
D15: Australia | E15: =Australia!D11 -> 705526 | F15: =Australia!C19 -> 95 | G15: -0.08 | H15: ●
G18: Status Legend
G19: ● | H19: On Track (≥5% growth)
G20: ● | H20: Monitor (0-5% growth)
G21: ● | H21: Action Needed (<0% growth)

Sheet United Kingdom
B2: United Kingdom Subsidiary Dashboard | F2: Summary
B3: Performance Tracker
B5: MONTHLY REVENUE
C6: Jan | D6: Feb | E6: Mar | F6: Apr | G6: May | H6: Jun | I6: Jul | J6: Aug | K6: Sep | L6: Oct | M6: Nov | N6: Dec | O6: YTD Total
B7: Revenue | C7: 84340 | D7: 84700 | E7: 101622 | F7: 100748 | G7: 95134 | H7: 94258 | I7: 87676 | J7: 77047 | K7: 90521 | L7: 84770 | M7: 100671 | N7: 105506 | O7: =SUM(C7:N7) -> 1106993
B9: KEY PERFORMANCE INDICATORS
B10: KPI | C10: Target | D10: Actual | E10: Variance | F10: Var % | G10: Status
B11: Annual Revenue | C11: 1100000 | D11: =O7 -> 1106993 | E11: =D11-C11 -> 6993 | F11: =IF(C11=0,0,(D11-C11)/C11) -> 0.0063572727 | G11: ●
B12: Operating Margin | C12: 0.22 | D12: 0.20012328 | E12: =D12-C12 -> -0.019876715 | F12: =IF(C12=0,0,(D12-C12)/C12) -> -0.090348705 | G12: ●
B13: Customer Satisfaction | C13: 85 | D13: 86 | E13: =D13-C13 -> 1 | F13: =IF(C13=0,0,(D13-C13)/C13) -> 0.011764706 | G13: ●
B14: Employee Retention % | C14: 92 | D14: 89 | E14: =D14-C14 -> -3 | F14: =IF(C14=0,0,(D14-C14)/C14) -> -0.032608696 | G14: ●
B15: New Customers | C15: 400 | D15: 339 | E15: =D15-C15 -> -61 | F15: =IF(C15=0,0,(D15-C15)/C15) -> -0.1525 | G15: ●
B16: Project Completion % | C16: 95 | D16: 90 | E16: =D16-C16 -> -5 | F16: =IF(C16=0,0,(D16-C16)/C16) -> -0.052631579 | G16: ●
B18: SUBSIDIARY INFORMATION
B19: Headcount | C19: 160
B20: Active Projects | C20: 8
B21: Year Established | C21: 2010
B22: Regional HQ | C22: No

Sheet United States
B2: USA Subsidiary Dashboard | E2: Summary
B3: Performance Tracker
B5: MONTHLY REVENUE
C6: Jan | D6: Feb | E6: Mar | F6: Apr | G6: May | H6: Jun | I6: Jul | J6: Aug | K6: Sep | L6: Oct | M6: Nov | N6: Dec | O6: YTD Total
B7: Revenue | C7: 193444 | D7: 203008 | E7: 226376 | F7: 257109 | G7: 202886 | H7: 194758 | I7: 175401 | J7: 197924 | K7: 211790 | L7: 218570 | M7: 248389 | N7: 240972 | O7: =SUM(C7:N7) -> 2570627
B9: KEY PERFORMANCE INDICATORS
B10: KPI | C10: Target | D10: Actual | E10: Variance | F10: Var % | G10: Status
B11: Annual Revenue | C11: 2500000 | D11: =O7 -> 2570627 | E11: =D11-C11 -> 70627 | F11: =IF(C11=0,0,(D11-C11)/C11) -> 0.0282508 | G11: ●
B12: Operating Margin | C12: 0.22 | D12: 0.21198327 | E12: =D12-C12 -> -0.0080167311 | F12: =IF(C12=0,0,(D12-C12)/C12) -> -0.036439687 | G12: ●
B13: Customer Satisfaction | C13: 85 | D13: 84 | E13: =D13-C13 -> -1 | F13: =IF(C13=0,0,(D13-C13)/C13) -> -0.011764706 | G13: ●
B14: Employee Retention % | C14: 92 | D14: 93 | E14: =D14-C14 -> 1 | F14: =IF(C14=0,0,(D14-C14)/C14) -> 0.010869565 | G14: ●
B15: New Customers | C15: 1125 | D15: 1156 | E15: =D15-C15 -> 31 | F15: =IF(C15=0,0,(D15-C15)/C15) -> 0.027555556 | G15: ●
B16: Project Completion % | C16: 95 | D16: 94 | E16: =D16-C16 -> -1 | F16: =IF(C16=0,0,(D16-C16)/C16) -> -0.010526316 | G16: ●
B18: SUBSIDIARY INFORMATION
B19: Headcount | C19: 450
B20: Active Projects | C20: 14
B21: Year Established | C21: 2008
B22: Regional HQ | C22: Yes

Sheet Canada
B2: Canada Subsidiary Dashboard | F2: Summary
B3: Performance Tracker
B5: MONTHLY REVENUE
C6: Jan | D6: Feb | E6: Mar | F6: Apr | G6: May | H6: Jun | I6: Jul | J6: Aug | K6: Sep | L6: Oct | M6: Nov | N6: Dec | O6: YTD Total
B7: Revenue | C7: 55639 | D7: 63764 | E7: 74083 | F7: 71512 | G7: 63816 | H7: 62410 | I7: 57868 | J7: 61302 | K7: 65224 | L7: 65281 | M7: 73103 | N7: 73808 | O7: =SUM(C7:N7) -> 787810
B9: KEY PERFORMANCE INDICATORS
B10: KPI | C10: Target | D10: Actual | E10: Variance | F10: Var % | G10: Status
B11: Annual Revenue | C11: 800000 | D11: =O7 -> 787810 | E11: =D11-C11 -> -12190 | F11: =IF(C11=0,0,(D11-C11)/C11) -> -0.0152375 | G11: ●
B12: Operating Margin | C12: 0.22 | D12: 0.22977034 | E12: =D12-C12 -> 0.0097703354 | F12: =IF(C12=0,0,(D12-C12)/C12) -> 0.044410616 | G12: ●
B13: Customer Satisfaction | C13: 85 | D13: 85 | E13: =D13-C13 -> 0 | F13: =IF(C13=0,0,(D13-C13)/C13) -> 0 | G13: ●
B14: Employee Retention % | C14: 92 | D14: 83 | E14: =D14-C14 -> -9 | F14: =IF(C14=0,0,(D14-C14)/C14) -> -0.097826087 | G14: ●
B15: New Customers | C15: 300 | D15: 323 | E15: =D15-C15 -> 23 | F15: =IF(C15=0,0,(D15-C15)/C15) -> 0.076666667 | G15: ●
B16: Project Completion % | C16: 95 | D16: 83 | E16: =D16-C16 -> -12 | F16: =IF(C16=0,0,(D16-C16)/C16) -> -0.12631579 | G16: ●
B18: SUBSIDIARY INFORMATION
B19: Headcount | C19: 120
B20: Active Projects | C20: 20
B21: Year Established | C21: 2012
B22: Regional HQ | C22: No

Sheet Germany
B2: Germany Subsidiary Dashboard | E2: Summary
B3: Performance Tracker
B5: MONTHLY REVENUE
C6: Jan | D6: Feb | E6: Mar | F6: Apr | G6: May | H6: Jun | I6: Jul | J6: Aug | K6: Sep | L6: Oct | M6: Nov | N6: Dec | O6: YTD Total
B7: Revenue | C7: 97049 | D7: 102239 | E7: 116047 | F7: 118396 | G7: 105485 | H7: 104415 | I7: 86098 | J7: 83262 | K7: 97047 | L7: 96283 | M7: 109682 | N7: 123149 | O7: =SUM(C7:N7) -> 1239152
B9: KEY PERFORMANCE INDICATORS
B10: KPI | C10: Target | D10: Actual | E10: Variance | F10: Var % | G10: Status
B11: Annual Revenue | C11: 1200000 | D11: =O7 -> 1239152 | E11: =D11-C11 -> 39152 | F11: =IF(C11=0,0,(D11-C11)/C11) -> 0.032626667 | G11: ●
B12: Operating Margin | C12: 0.22 | D12: 0.20776874 | E12: =D12-C12 -> -0.01223126 | F12: =IF(C12=0,0,(D12-C12)/C12) -> -0.055596636 | G12: ●
B13: Customer Satisfaction | C13: 85 | D13: 86 | E13: =D13-C13 -> 1 | F13: =IF(C13=0,0,(D13-C13)/C13) -> 0.011764706 | G13: ●
B14: Employee Retention % | C14: 92 | D14: 87 | E14: =D14-C14 -> -5 | F14: =IF(C14=0,0,(D14-C14)/C14) -> -0.054347826 | G14: ●
B15: New Customers | C15: 450 | D15: 522 | E15: =D15-C15 -> 72 | F15: =IF(C15=0,0,(D15-C15)/C15) -> 0.16 | G15: ●
B16: Project Completion % | C16: 95 | D16: 88 | E16: =D16-C16 -> -7 | F16: =IF(C16=0,0,(D16-C16)/C16) -> -0.073684211 | G16: ●
B18: SUBSIDIARY INFORMATION
B19: Headcount | C19: 180
B20: Active Projects | C20: 16
B21: Year Established | C21: 2010
B22: Regional HQ | C22: Yes

Sheet Austria
B2: Austria Subsidiary Dashboard | F2: Summary
B3: Performance Tracker
B5: MONTHLY REVENUE
C6: Jan | D6: Feb | E6: Mar | F6: Apr | G6: May | H6: Jun | I6: Jul | J6: Aug | K6: Sep | L6: Oct | M6: Nov | N6: Dec | O6: YTD Total
B7: Revenue | C7: 28783 | D7: 33660 | E7: 36878 | F7: 38852 | G7: 35455 | H7: 32796 | I7: 28652 | J7: 32388 | K7: 33384 | L7: 31151 | M7: 35555 | N7: 35939 | O7: =SUM(C7:N7) -> 403493
B9: KEY PERFORMANCE INDICATORS
B10: KPI | C10: Target | D10: Actual | E10: Variance | F10: Var % | G10: Status
B11: Annual Revenue | C11: 400000 | D11: =O7 -> 403493 | E11: =D11-C11 -> 3493 | F11: =IF(C11=0,0,(D11-C11)/C11) -> 0.0087325 | G11: ●
B12: Operating Margin | C12: 0.22 | D12: 0.23927724 | E12: =D12-C12 -> 0.019277238 | F12: =IF(C12=0,0,(D12-C12)/C12) -> 0.087623809 | G12: ●
B13: Customer Satisfaction | C13: 85 | D13: 82 | E13: =D13-C13 -> -3 | F13: =IF(C13=0,0,(D13-C13)/C13) -> -0.035294118 | G13: ●
B14: Employee Retention % | C14: 92 | D14: 81 | E14: =D14-C14 -> -11 | F14: =IF(C14=0,0,(D14-C14)/C14) -> -0.11956522 | G14: ●
B15: New Customers | C15: 162 | D15: 149 | E15: =D15-C15 -> -13 | F15: =IF(C15=0,0,(D15-C15)/C15) -> -0.080246914 | G15: ●
B16: Project Completion % | C16: 95 | D16: 96 | E16: =D16-C16 -> 1 | F16: =IF(C16=0,0,(D16-C16)/C16) -> 0.010526316 | G16: ●
B18: SUBSIDIARY INFORMATION
B19: Headcount | C19: 65
B20: Active Projects | C20: 24
B21: Year Established | C21: 2012
B22: Regional HQ | C22: No

Sheet France
B2: France Subsidiary Dashboard | F2: Summary
B3: Performance Tracker
B5: MONTHLY REVENUE
C6: Jan | D6: Feb | E6: Mar | F6: Apr | G6: May | H6: Jun | I6: Jul | J6: Aug | K6: Sep | L6: Oct | M6: Nov | N6: Dec | O6: YTD Total
B7: Revenue | C7: 76620 | D7: 83736 | E7: 83925 | F7: 94256 | G7: 81468 | H7: 79634 | I7: 68591 | J7: 72856 | K7: 74246 | L7: 78340 | M7: 90367 | N7: 97652 | O7: =SUM(C7:N7) -> 981691
B9: KEY PERFORMANCE INDICATORS
B10: KPI | C10: Target | D10: Actual | E10: Variance | F10: Var % | G10: Status
B11: Annual Revenue | C11: 950000 | D11: =O7 -> 981691 | E11: =D11-C11 -> 31691 | F11: =IF(C11=0,0,(D11-C11)/C11) -> 0.033358947 | G11: ●
B12: Operating Margin | C12: 0.22 | D12: 0.20438368 | E12: =D12-C12 -> -0.015616323 | F12: =IF(C12=0,0,(D12-C12)/C12) -> -0.070983285 | G12: ●
B13: Customer Satisfaction | C13: 85 | D13: 84 | E13: =D13-C13 -> -1 | F13: =IF(C13=0,0,(D13-C13)/C13) -> -0.011764706 | G13: ●
B14: Employee Retention % | C14: 92 | D14: 83 | E14: =D14-C14 -> -9 | F14: =IF(C14=0,0,(D14-C14)/C14) -> -0.097826087 | G14: ●
B15: New Customers | C15: 350 | D15: 406 | E15: =D15-C15 -> 56 | F15: =IF(C15=0,0,(D15-C15)/C15) -> 0.16 | G15: ●
B16: Project Completion % | C16: 95 | D16: 94 | E16: =D16-C16 -> -1 | F16: =IF(C16=0,0,(D16-C16)/C16) -> -0.010526316 | G16: ●
B18: SUBSIDIARY INFORMATION
B19: Headcount | C19: 140
B20: Active Projects | C20: 17
B21: Year Established | C21: 2018
B22: Regional HQ | C22: No

Sheet India
B2: India Subsidiary Dashboard | E2: Summary
B3: Performance Tracker
B5: MONTHLY REVENUE
C6: Jan | D6: Feb | E6: Mar | F6: Apr | G6: May | H6: Jun | I6: Jul | J6: Aug | K6: Sep | L6: Oct | M6: Nov | N6: Dec | O6: YTD Total
B7: Revenue | C7: 45784 | D7: 47222 | E7: 59915 | F7: 57862 | G7: 52229 | H7: 50242 | I7: 41404 | J7: 43733 | K7: 46155 | L7: 53432 | M7: 60984 | N7: 60551 | O7: =SUM(C7:N7) -> 619513
B9: KEY PERFORMANCE INDICATORS
B10: KPI | C10: Target | D10: Actual | E10: Variance | F10: Var % | G10: Status
B11: Annual Revenue | C11: 600000 | D11: =O7 -> 619513 | E11: =D11-C11 -> 19513 | F11: =IF(C11=0,0,(D11-C11)/C11) -> 0.032521667 | G11: ●
B12: Operating Margin | C12: 0.22 | D12: 0.19082306 | E12: =D12-C12 -> -0.029176939 | F12: =IF(C12=0,0,(D12-C12)/C12) -> -0.13262245 | G12: ●
B13: Customer Satisfaction | C13: 85 | D13: 89 | E13: =D13-C13 -> 4 | F13: =IF(C13=0,0,(D13-C13)/C13) -> 0.047058824 | G13: ●
B14: Employee Retention % | C14: 92 | D14: 95 | E14: =D14-C14 -> 3 | F14: =IF(C14=0,0,(D14-C14)/C14) -> 0.032608696 | G14: ●
B15: New Customers | C15: 700 | D15: 551 | E15: =D15-C15 -> -149 | F15: =IF(C15=0,0,(D15-C15)/C15) -> -0.21285714 | G15: ●
B16: Project Completion % | C16: 95 | D16: 88 | E16: =D16-C16 -> -7 | F16: =IF(C16=0,0,(D16-C16)/C16) -> -0.073684211 | G16: ●
B18: SUBSIDIARY INFORMATION
B19: Headcount | C19: 280
B20: Active Projects | C20: 10
B21: Year Established | C21: 2018
B22: Regional HQ | C22: No

Sheet China
B2: China Subsidiary Dashboard | E2: Summary
B3: Performance Tracker
B5: MONTHLY REVENUE
C6: Jan | D6: Feb | E6: Mar | F6: Apr | G6: May | H6: Jun | I6: Jul | J6: Aug | K6: Sep | L6: Oct | M6: Nov | N6: Dec | O6: YTD Total
B7: Revenue | C7: 140742 | D7: 141081 | E7: 171817 | F7: 173874 | G7: 144361 | H7: 158938 | I7: 133339 | J7: 128774 | K7: 150943 | L7: 155518 | M7: 164251 | N7: 167303 | O7: =SUM(C7:N7) -> 1830941
B9: KEY PERFORMANCE INDICATORS
B10: KPI | C10: Target | D10: Actual | E10: Variance | F10: Var % | G10: Status
B11: Annual Revenue | C11: 1800000 | D11: =O7 -> 1830941 | E11: =D11-C11 -> 30941 | F11: =IF(C11=0,0,(D11-C11)/C11) -> 0.017189444 | G11: ●
B12: Operating Margin | C12: 0.22 | D12: 0.22989195 | E12: =D12-C12 -> 0.0098919518 | F12: =IF(C12=0,0,(D12-C12)/C12) -> 0.044963417 | G12: ●
B13: Customer Satisfaction | C13: 85 | D13: 83 | E13: =D13-C13 -> -2 | F13: =IF(C13=0,0,(D13-C13)/C13) -> -0.023529412 | G13: ●
B14: Employee Retention % | C14: 92 | D14: 89 | E14: =D14-C14 -> -3 | F14: =IF(C14=0,0,(D14-C14)/C14) -> -0.032608696 | G14: ●
B15: New Customers | C15: 875 | D15: 703 | E15: =D15-C15 -> -172 | F15: =IF(C15=0,0,(D15-C15)/C15) -> -0.19657143 | G15: ●
B16: Project Completion % | C16: 95 | D16: 84 | E16: =D16-C16 -> -11 | F16: =IF(C16=0,0,(D16-C16)/C16) -> -0.11578947 | G16: ●
B18: SUBSIDIARY INFORMATION
B19: Headcount | C19: 350
B20: Active Projects | C20: 18
B21: Year Established | C21: 2008
B22: Regional HQ | C22: Yes

Sheet Australia
B2: Australia Subsidiary Dashboard | F2: Summary
B3: Performance Tracker
B5: MONTHLY REVENUE
C6: Jan | D6: Feb | E6: Mar | F6: Apr | G6: May | H6: Jun | I6: Jul | J6: Aug | K6: Sep | L6: Oct | M6: Nov | N6: Dec | O6: YTD Total
B7: Revenue | C7: 53241 | D7: 55814 | E7: 64080 | F7: 62478 | G7: 59556 | H7: 55803 | I7: 55905 | J7: 55520 | K7: 54328 | L7: 55888 | M7: 68897 | N7: 64016 | O7: =SUM(C7:N7) -> 705526
B9: KEY PERFORMANCE INDICATORS
B10: KPI | C10: Target | D10: Actual | E10: Variance | F10: Var % | G10: Status
B11: Annual Revenue | C11: 700000 | D11: =O7 -> 705526 | E11: =D11-C11 -> 5526 | F11: =IF(C11=0,0,(D11-C11)/C11) -> 0.0078942857 | G11: ●
B12: Operating Margin | C12: 0.22 | D12: 0.24874394 | E12: =D12-C12 -> 0.02874394 | F12: =IF(C12=0,0,(D12-C12)/C12) -> 0.13065427 | G12: ●
B13: Customer Satisfaction | C13: 85 | D13: 85 | E13: =D13-C13 -> 0 | F13: =IF(C13=0,0,(D13-C13)/C13) -> 0 | G13: ●
B14: Employee Retention % | C14: 92 | D14: 88 | E14: =D14-C14 -> -4 | F14: =IF(C14=0,0,(D14-C14)/C14) -> -0.043478261 | G14: ●
B15: New Customers | C15: 237 | D15: 261 | E15: =D15-C15 -> 24 | F15: =IF(C15=0,0,(D15-C15)/C15) -> 0.10126582 | G15: ●
B16: Project Completion % | C16: 95 | D16: 93 | E16: =D16-C16 -> -2 | F16: =IF(C16=0,0,(D16-C16)/C16) -> -0.021052632 | G16: ●
B18: SUBSIDIARY INFORMATION
B19: Headcount | C19: 95
B20: Active Projects | C20: 14
B21: Year Established | C21: 2008
B22: Regional HQ | C22: No

Sheet Instructions for Reporting
B2: Reporting Instructions
B4: Global Subsidiaries & Cost Center Dashboard
B7: Overview
B9: This workbook contains consolidated performance data for all global subsidiaries and cost centers. The file is structured
B10: to provide both high-level summaries and detailed drill-downs for regional and departmental analysis.
B13: File Structure
B15: Summary Sheets
B17: Summary: Consolidated view of all subsidiary performance
B18: Cost Center Summary: Company-wide cost center overview
B20: Regional Subsidiary Sheets
B22: Individual dashboards for each geographic region:
B23: United Kingdom, United States, Canada, Germany, Austria, France, India, China, Australia
... B85: For questions about reporting procedures, contact Finance Operations team. For technical issues with the file, contact IT Support.

Sheet Cost Center Summary
B2: Cost Center Overview
B3: Company-Wide Cost Center Summary
B5: ALL COST CENTERS
B6: Code | C6: Name | D6: Budget | E6: Actual | F6: Variance | G6: Var % | H6: Status
B7: CC-1000 | C7: Manufacturing Operations | D7: ='CC-1000'!C21 -> 4500000 | E7: ='CC-1000'!D21 -> 4433679 | F7: =E7-D7 -> -66321 | G7: =IF(D7=0,0,(E7-D7)/D7) -> -0.014738 | H7: ● | J7: NOTE: Code For example CC-1000 -> Right Click -> Link -> Place in This Document -> CC-1000 (Spreadsheet) and match Cell -> Enter. Repeat for the others.
B8: CC-1100 | C8: Quality Assurance | D8: ='CC-1100'!C21 -> 1200000 | E8: ='CC-1100'!D21 -> 1184834 | F8: =E8-D8 -> -15166 | G8: =IF(D8=0,0,(E8-D8)/D8) -> -0.012638333 | H8: ●
B9: CC-2000 | C9: Sales | D9: ='CC-2000'!C21 -> 3200000 | E9: ='CC-2000'!D21 -> 3203927 | F9: =E9-D9 -> 3927 | G9: =IF(D9=0,0,(E9-D9)/D9) -> 0.0012271875 | H9: ●
B10: CC-2100 | C10: Marketing | D10: ='CC-2100'!C21 -> 2800000 | E10: ='CC-2100'!D21 -> 2813396 | F10: =E10-D10 -> 13396 | G10: =IF(D10=0,0,(E10-D10)/D10) -> 0.0047842857 | H10: ●
B11: CC-3000 | C11: Finance & Accounting | D11: ='CC-3000'!C21 -> 1800000 | E11: ='CC-3000'!D21 -> 1784468 | F11: =E11-D11 -> -15532 | G11: =IF(D11=0,0,(E11-D11)/D11) -> -0.0086288889 | H11: ●
B12: CC-3100 | C12: Human Resources | D12: ='CC-3100'!C21 -> 1500000 | E12: ='CC-3100'!D21 -> 1476705 | F12: =E12-D12 -> -23295 | G12: =IF(D12=0,0,(E12-D12)/D12) -> -0.01553 | H12: ●
B13: CC-3200 | C13: IT & Digital | D13: ='CC-3200'!C21 -> 3500000 | E13: ='CC-3200'!D21 -> 4402676 | F13: =E13-D13 -> 902676 | G13: =IF(D13=0,0,(E13-D13)/D13) -> 0.25790743 | H13: ●
B14: CC-3300 | C14: Legal & Compliance | D14: ='CC-3300'!C21 -> 1400000 | E14: ='CC-3300'!D21 -> 1424744 | F14: =E14-D14 -> 24744 | G14: =IF(D14=0,0,(E14-D14)/D14) -> 0.017674286 | H14: ●
B15: CC-4000 | C15: General & Administration | D15: ='CC-4000'!C21 -> 2200000 | E15: ='CC-4000'!D21 -> 2213126 | F15: =E15-D15 -> 13126 | G15: =IF(D15=0,0,(E15-D15)/D15) -> 0.0059663636 | H15: ●
B16: CC-5000 | C16: Facilities Management | D16: ='CC-5000'!C21 -> 2400000 | E16: ='CC-5000'!D21 -> 2417248 | F16: =E16-D16 -> 17248 | G16: =IF(D16=0,0,(E16-D16)/D16) -> 0.0071866667 | H16: ●
B17: TOTAL | D17: =SUM(D7:D16) -> 24500000 | E17: =SUM(E7:E16) -> 25354803 | F17: =E17-D17 -> 854803 | G17: =IF(D17=0,0,(E17-D17)/D17) -> 0.034889918 | H17: ●
B19: Status Legend
B20: ● | C20: Under/On Budget
B21: ● | C21: Over Budget (≤10%)
B22: ● | C22: Over Budget (>10%)

Sheet CC-1000
B2: CC-1000 - Manufacturing Operations | H2: Cost Center Summary | I2: NOTE: Type in Summary (text) -> Right Click -> Link/HyperLink-> Place in This Document ->Cost Center Summary (Spreadsheet) and match Cell -> Enter. Repeat for the others.
B3: Cost Center Report
B5: MONTHLY SPEND BY CATEGORY
C6: Jan | D6: Feb | E6: Mar | F6: Apr | G6: May | H6: Jun | I6: Jul | J6: Aug | K6: Sep | L6: Oct | M6: Nov | N6: Dec | O6: YTD Total
B7: Raw Materials | C7: 64928 | D7: 65711 | E7: 72912 | F7: 66173 | G7: 84026 | H7: 64608 | I7: 75814 | J7: 71224 | K7: 82921 | L7: 67342 | M7: 71337 | N7: 71260 | O7: =SUM(C7:N7) -> 858256
B8: Equipment Maintenance | C8: 69266 | D8: 63787 | E8: 73566 | F8: 65721 | G8: 77195 | H8: 65322 | I8: 70847 | J8: 73837 | K8: 84121 | L8: 65837 | M8: 66948 | N8: 81526 | O8: =SUM(C8:N8) -> 857973
B9: Utilities | C9: 64227 | D9: 84250 | E9: 76651 | F9: 69719 | G9: 82601 | H9: 81047 | I9: 71477 | J9: 81783 | K9: 68404 | L9: 77450 | M9: 75609 | N9: 81960 | O9: =SUM(C9:N9) -> 915178
B10: Contract Labor | C10: 70843 | D10: 72710 | E10: 81058 | F10: 75286 | G10: 79158 | H10: 78112 | I10: 78749 | J10: 83777 | K10: 74688 | L10: 78790 | M10: 72176 | N10: 64466 | O10: =SUM(C10:N10) -> 909813
B11: Safety & Compliance | C11: 80718 | D11: 67832 | E11: 82204 | F11: 84307 | G11: 78556 | H11: 67577 | I11: 71330 | J11: 72551 | K11: 65399 | L11: 74027 | M11: 76646 | N11: 71312 | O11: =SUM(C11:N11) -> 892459
B12: Total | C12: =SUM(C7:C11) -> 349982 | D12: =SUM(D7:D11) -> 354290 | E12: =SUM(E7:E11) -> 386391 | F12: =SUM(F7:F11) -> 361206 | G12: =SUM(G7:G11) -> 401536 | H12: =SUM(H7:H11) -> 356666 | I12: =SUM(I7:I11) -> 368217 | J12: =SUM(J7:J11) -> 383172 | ... O12: =SUM(O7:O11) -> 4433679
B14: BUDGET VS ACTUAL
B15: Category | C15: Budget | D15: Actual | E15: Variance | F15: Var % | G15: Status
B16: Raw Materials | C16: 900000 | D16: =O7 -> 858256 | E16: =D16-C16 -> -41744 | F16: =IF(C16=0,0,(D16-C16)/C16) -> -0.046382222 | G16: ●
B17: Equipment Maintenance | C17: 900000 | D17: =O8 -> 857973 | E17: =D17-C17 -> -42027 | F17: =IF(C17=0,0,(D17-C17)/C17) -> -0.046696667 | G17: ●
B18: Utilities | C18: 900000 | D18: =O9 -> 915178 | E18: =D18-C18 -> 15178 | F18: =IF(C18=0,0,(D18-C18)/C18) -> 0.016864444 | G18: ●
B19: Contract Labor | C19: 900000 | D19: =O10 -> 909813 | E19: =D19-C19 -> 9813 | F19: =IF(C19=0,0,(D19-C19)/C19) -> 0.010903333 | G19: ●
B20: Safety & Compliance | C20: 900000 | D20: =O11 -> 892459 | E20: =D20-C20 -> -7541 | F20: =IF(C20=0,0,(D20-C20)/C20) -> -0.0083788889 | G20: ●
B21: Total | C21: =SUM(C16:C20) -> 4500000 | D21: =SUM(D16:D20) -> 4433679 | E21: =D21-C21 -> -66321 | F21: =IF(C21=0,0,(D21-C21)/C21) -> -0.014738 | G21: ●
B23: COST CENTER INFORMATION
B24: Manager | C24: Hans Mueller
B25: Department | C25: Manufacturing Operations
B26: Headcount | C26: 285
B27: Location | C27: Regional Office - EU

Sheet CC-1100
B2: CC-1100 - Quality Assurance | H2: Cost Center Summary
B3: Cost Center Report
B5: MONTHLY SPEND BY CATEGORY
C6: Jan | D6: Feb | E6: Mar | F6: Apr | G6: May | H6: Jun | I6: Jul | J6: Aug | K6: Sep | L6: Oct | M6: Nov | N6: Dec | O6: YTD Total
B7: Testing Equipment | C7: 18134 | D7: 17528 | E7: 20769 | F7: 17076 | G7: 19111 | H7: 18374 | I7: 20191 | J7: 21341 | K7: 22454 | L7: 20832 | M7: 22950 | N7: 22784 | O7: =SUM(C7:N7) -> 241544
B8: Lab Supplies | C8: 20779 | D8: 18400 | E8: 19902 | F8: 18065 | G8: 22951 | H8: 19666 | I8: 21509 | J8: 17264 | K8: 17808 | L8: 18159 | M8: 18538 | N8: 19112 | O8: =SUM(C8:N8) -> 232153
B9: Certifications | C9: 18631 | D9: 19605 | E9: 19522 | F9: 17651 | G9: 17375 | H9: 19130 | I9: 17532 | J9: 19599 | K9: 17051 | L9: 20214 | M9: 17440 | N9: 21165 | O9: =SUM(C9:N9) -> 224915
B10: Personnel Costs | C10: 19425 | D10: 22912 | E10: 18575 | F10: 19835 | G10: 21504 | H10: 19008 | I10: 19090 | J10: 20834 | K10: 22818 | L10: 22303 | M10: 19514 | N10: 21306 | O10: =SUM(C10:N10) -> 247124
B11: External Audits | C11: 21074 | D11: 19232 | E11: 18409 | F11: 17470 | G11: 22273 | H11: 17342 | I11: 20112 | J11: 20225 | K11: 17876 | L11: 20935 | M11: 22494 | N11: 21656 | O11: =SUM(C11:N11) -> 239098
B12: Total | C12: =SUM(C7:C11) -> 98043 | D12: =SUM(D7:D11) -> 97677 | E12: =SUM(E7:E11) -> 97177 | F12: =SUM(F7:F11) -> 90097 | G12: =SUM(G7:G11) -> 103214 | H12: =SUM(H7:H11) -> 93520 | I12: =SUM(I7:I11) -> 98434 | J12: =SUM(J7:J11) -> 99263 | ... O12: =SUM(O7:O11) -> 1184834
B14: BUDGET VS ACTUAL
B15: Category | C15: Budget | D15: Actual | E15: Variance | F15: Var % | G15: Status
B16: Testing Equipment | C16: 240000 | D16: =O7 -> 241544 | E16: =D16-C16 -> 1544 | F16: =IF(C16=0,0,(D16-C16)/C16) -> 0.0064333333 | G16: ●
B17: Lab Supplies | C17: 240000 | D17: =O8 -> 232153 | E17: =D17-C17 -> -7847 | F17: =IF(C17=0,0,(D17-C17)/C17) -> -0.032695833 | G17: ●
B18: Certifications | C18: 240000 | D18: =O9 -> 224915 | E18: =D18-C18 -> -15085 | F18: =IF(C18=0,0,(D18-C18)/C18) -> -0.062854167 | G18: ●
B19: Personnel Costs | C19: 240000 | D19: =O10 -> 247124 | E19: =D19-C19 -> 7124 | F19: =IF(C19=0,0,(D19-C19)/C19) -> 0.029683333 | G19: ●
B20: External Audits | C20: 240000 | D20: =O11 -> 239098 | E20: =D20-C20 -> -902 | F20: =IF(C20=0,0,(D20-C20)/C20) -> -0.0037583333 | G20: ●
B21: Total | C21: =SUM(C16:C20) -> 1200000 | D21: =SUM(D16:D20) -> 1184834 | E21: =D21-C21 -> -15166 | F21: =IF(C21=0,0,(D21-C21)/C21) -> -0.012638333 | G21: ●
B23: COST CENTER INFORMATION
B24: Manager | C24: Yuki Tanaka
B25: Department | C25: Quality Assurance
B26: Headcount | C26: 45
B27: Location | C27: Regional Office - APAC

Sheet CC-2000
B2: CC-2000 - Sales | H2: Cost Center Summary
B3: Cost Center Report
B5: MONTHLY SPEND BY CATEGORY
C6: Jan | D6: Feb | E6: Mar | F6: Apr | G6: May | H6: Jun | I6: Jul | J6: Aug | K6: Sep | L6: Oct | M6: Nov | N6: Dec | O6: YTD Total
B7: Commissions | C7: 51561 | D7: 47356 | E7: 60932 | F7: 53606 | G7: 55407 | H7: 58169 | I7: 51513 | J7: 46326 | K7: 47509 | L7: 56028 | M7: 50925 | N7: 59270 | O7: =SUM(C7:N7) -> 638602
B8: Travel & Entertainment | C8: 57175 | D8: 61020 | E8: 56034 | F8: 50194 | G8: 57991 | H8: 45785 | I8: 53678 | J8: 59275 | K8: 53568 | L8: 47531 | M8: 53335 | N8: 54060 | O8: =SUM(C8:N8) -> 649646
B9: Client Events | C9: 51237 | D9: 59628 | E9: 50774 | F9: 49681 | G9: 53434 | H9: 48585 | I9: 50486 | J9: 51704 | K9: 60345 | L9: 46619 | M9: 48486 | N9: 48525 | O9: =SUM(C9:N9) -> 619504
B10: CRM Software | C10: 61257 | D10: 59586 | E10: 48439 | F10: 54367 | G10: 46694 | H10: 50405 | I10: 50791 | J10: 53936 | K10: 60203 | L10: 58277 | M10: 53880 | N10: 57910 | O10: =SUM(C10:N10) -> 655745
B11: Sales Training | C11: 53076 | D11: 57022 | E11: 57764 | F11: 49442 | G11: 58657 | H11: 54580 | I11: 53111 | J11: 51666 | K11: 48919 | L11: 53353 | M11: 47351 | N11: 55489 | O11: =SUM(C11:N11) -> 640430
B12: Total | C12: =SUM(C7:C11) -> 274306 | D12: =SUM(D7:D11) -> 284612 | E12: =SUM(E7:E11) -> 273943 | F12: =SUM(F7:F11) -> 257290 | G12: =SUM(G7:G11) -> 272183 | H12: =SUM(H7:H11) -> 257524 | I12: =SUM(I7:I11) -> 259579 | J12: =SUM(J7:J11) -> 262907 | ... O12: =SUM(O7:O11) -> 3203927
B14: BUDGET VS ACTUAL
B15: Category | C15: Budget | D15: Actual | E15: Variance | F15: Var % | G15: Status
B16: Commissions | C16: 640000 | D16: =O7 -> 638602 | E16: =D16-C16 -> -1398 | F16: =IF(C16=0,0,(D16-C16)/C16) -> -0.002184375 | G16: ●
B17: Travel & Entertainment | C17: 640000 | D17: =O8 -> 649646 | E17: =D17-C17 -> 9646 | F17: =IF(C17=0,0,(D17-C17)/C17) -> 0.015071875 | G17: ●
B18: Client Events | C18: 640000 | D18: =O9 -> 619504 | E18: =D18-C18 -> -20496 | F18: =IF(C18=0,0,(D18-C18)/C18) -> -0.032025 | G18: ●
B19: CRM Software | C19: 640000 | D19: =O10 -> 655745 | E19: =D19-C19 -> 15745 | F19: =IF(C19=0,0,(D19-C19)/C19) -> 0.024601563 | G19: ●
B20: Sales Training | C20: 640000 | D20: =O11 -> 640430 | E20: =D20-C20 -> 430 | F20: =IF(C20=0,0,(D20-C20)/C20) -> 0.000671875 | G20: ●
B21: Total | C21: =SUM(C16:C20) -> 3200000 | D21: =SUM(D16:D20) -> 3203927 | E21: =D21-C21 -> 3927 | F21: =IF(C21=0,0,(D21-C21)/C21) -> 0.0012271875 | G21: ●
B23: COST CENTER INFORMATION
B24: Manager | C24: Michael Roberts
B25: Department | C25: Sales
B26: Headcount | C26: 120
B27: Location | C27: HQ

Sheet CC-2100
B2: CC-2100 - Marketing | H2: Cost Center Summary
B3: Cost Center Report
B5: MONTHLY SPEND BY CATEGORY
C6: Jan | D6: Feb | E6: Mar | F6: Apr | G6: May | H6: Jun | I6: Jul | J6: Aug | K6: Sep | L6: Oct | M6: Nov | N6: Dec | O6: YTD Total
B7: Advertising | C7: 52242 | D7: 50734 | E7: 48194 | F7: 46589 | G7: 49407 | H7: 41379 | I7: 40400 | J7: 51729 | K7: 44732 | L7: 49031 | M7: 45557 | N7: 44688 | O7: =SUM(C7:N7) -> 564682
B8: Digital Campaigns | C8: 50450 | D8: 44469 | E8: 50218 | F8: 51153 | G8: 42196 | H8: 53347 | I8: 40540 | J8: 45472 | K8: 46673 | L8: 51277 | M8: 42114 | N8: 47493 | O8: =SUM(C8:N8) -> 565402
B9: Events & Sponsorships | C9: 44825 | D9: 52570 | E9: 41379 | F9: 43382 | G9: 51143 | H9: 44177 | I9: 52885 | J9: 40389 | K9: 45104 | L9: 41171 | M9: 47696 | N9: 53150 | O9: =SUM(C9:N9) -> 557871
B10: Agency Fees | C10: 44212 | D10: 48722 | E10: 43389 | F10: 45815 | G10: 47667 | H10: 43144 | I10: 49333 | J10: 46680 | K10: 52343 | L10: 43516 | M10: 53034 | N10: 42217 | O10: =SUM(C10:N10) -> 560072
B11: Content Production | C11: 39945 | D11: 48909 | E11: 49939 | F11: 46349 | G11: 40265 | H11: 53640 | I11: 41648 | J11: 51853 | K11: 52148 | L11: 42758 | M11: 51761 | N11: 46154 | O11: =SUM(C11:N11) -> 565369
B12: Total | C12: =SUM(C7:C11) -> 231674 | D12: =SUM(D7:D11) -> 245404 | E12: =SUM(E7:E11) -> 233119 | F12: =SUM(F7:F11) -> 233288 | G12: =SUM(G7:G11) -> 230678 | H12: =SUM(H7:H11) -> 235687 | I12: =SUM(I7:I11) -> 224806 | J12: =SUM(J7:J11) -> 236123 | ... O12: =SUM(O7:O11) -> 2813396
B14: BUDGET VS ACTUAL
B15: Category | C15: Budget | D15: Actual | E15: Variance | F15: Var % | G15: Status
B16: Advertising | C16: 560000 | D16: =O7 -> 564682 | E16: =D16-C16 -> 4682 | F16: =IF(C16=0,0,(D16-C16)/C16) -> 0.0083607143 | G16: ●
B17: Digital Campaigns | C17: 560000 | D17: =O8 -> 565402 | E17: =D17-C17 -> 5402 | F17: =IF(C17=0,0,(D17-C17)/C17) -> 0.0096464286 | G17: ●
B18: Events & Sponsorships | C18: 560000 | D18: =O9 -> 557871 | E18: =D18-C18 -> -2129 | F18: =IF(C18=0,0,(D18-C18)/C18) -> -0.0038017857 | G18: ●
B19: Agency Fees | C19: 560000 | D19: =O10 -> 560072 | E19: =D19-C19 -> 72 | F19: =IF(C19=0,0,(D19-C19)/C19) -> 0.00012857143 | G19: ●
B20: Content Production | C20: 560000 | D20: =O11 -> 565369 | E20: =D20-C20 -> 5369 | F20: =IF(C20=0,0,(D20-C20)/C20) -> 0.0095875 | G20: ●
B21: Total | C21: =SUM(C16:C20) -> 2800000 | D21: =SUM(D16:D20) -> 2813396 | E21: =D21-C21 -> 13396 | F21: =IF(C21=0,0,(D21-C21)/C21) -> 0.0047842857 | G21: ●
B23: COST CENTER INFORMATION
B24: Manager | C24: Sofia Martinez
B25: Department | C25: Marketing
B26: Headcount | C26: 65
B27: Location | C27: HQ

Sheet CC-3000
B2: CC-3000 - Finance & Accounting | H2: Cost Center Summary
B3: Cost Center Report
B5: MONTHLY SPEND BY CATEGORY
C6: Jan | D6: Feb | E6: Mar | F6: Apr | G6: May | H6: Jun | I6: Jul | J6: Aug | K6: Sep | L6: Oct | M6: Nov | N6: Dec | O6: YTD Total
B7: Personnel Costs | C7: 33596 | D7: 33487 | E7: 32468 | F7: 28098 | G7: 30720 | H7: 34331 | I7: 28385 | J7: 28978 | K7: 31691 | L7: 26063 | M7: 27780 | N7: 27012 | O7: =SUM(C7:N7) -> 362609
B8: Audit Fees | C8: 29244 | D8: 29324 | E8: 30963 | F8: 29971 | G8: 26982 | H8: 25919 | I8: 30222 | J8: 32374 | K8: 33842 | L8: 33056 | M8: 28224 | N8: 33291 | O8: =SUM(C8:N8) -> 363412
B9: Banking Fees | C9: 29706 | D9: 28042 | E9: 26329 | F9: 29484 | G9: 30404 | H9: 28013 | I9: 27257 | J9: 33968 | K9: 26109 | L9: 33954 | M9: 29157 | N9: 32623 | O9: =SUM(C9:N9) -> 355046
B10: Financial Software | C10: 26498 | D10: 30630 | E10: 32355 | F10: 29424 | G10: 28708 | H10: 29938 | I10: 27250 | J10: 27404 | K10: 27671 | L10: 25838 | M10: 33690 | N10: 26160 | O10: =SUM(C10:N10) -> 345566
B11: Consulting Services | C11: 33844 | D11: 25598 | E11: 31405 | F11: 30422 | G11: 25876 | H11: 33973 | I11: 32076 | J11: 33412 | K11: 29420 | L11: 28122 | M11: 27173 | N11: 26514 | O11: =SUM(C11:N11) -> 357835
B12: Total | C12: =SUM(C7:C11) -> 152888 | D12: =SUM(D7:D11) -> 147081 | E12: =SUM(E7:E11) -> 153520 | F12: =SUM(F7:F11) -> 147399 | G12: =SUM(G7:G11) -> 142690 | H12: =SUM(H7:H11) -> 152174 | I12: =SUM(I7:I11) -> 145190 | J12: =SUM(J7:J11) -> 156136 | ... O12: =SUM(O7:O11) -> 1784468
B14: BUDGET VS ACTUAL
B15: Category | C15: Budget | D15: Actual | E15: Variance | F15: Var % | G15: Status
B16: Personnel Costs | C16: 360000 | D16: =O7 -> 362609 | E16: =D16-C16 -> 2609 | F16: =IF(C16=0,0,(D16-C16)/C16) -> 0.0072472222 | G16: ●
B17: Audit Fees | C17: 360000 | D17: =O8 -> 363412 | E17: =D17-C17 -> 3412 | F17: =IF(C17=0,0,(D17-C17)/C17) -> 0.0094777778 | G17: ●
B18: Banking Fees | C18: 360000 | D18: =O9 -> 355046 | E18: =D18-C18 -> -4954 | F18: =IF(C18=0,0,(D18-C18)/C18) -> -0.013761111 | G18: ●
B19: Financial Software | C19: 360000 | D19: =O10 -> 345566 | E19: =D19-C19 -> -14434 | F19: =IF(C19=0,0,(D19-C19)/C19) -> -0.040094444 | G19: ●
B20: Consulting Services | C20: 360000 | D20: =O11 -> 357835 | E20: =D20-C20 -> -2165 | F20: =IF(C20=0,0,(D20-C20)/C20) -> -0.0060138889 | G20: ●
B21: Total | C21: =SUM(C16:C20) -> 1800000 | D21: =SUM(D16:D20) -> 1784468 | E21: =D21-C21 -> -15532 | F21: =IF(C21=0,0,(D21-C21)/C21) -> -0.0086288889 | G21: ●
B23: COST CENTER INFORMATION
B24: Manager | C24: Charlotte Dubois
B25: Department | C25: Finance & Accounting
B26: Headcount | C26: 55
B27: Location | C27: Shared Services Center

Sheet CC-3100
B2: CC-3100 - Human Resources | H2: Cost Center Summary
B3: Cost Center Report
B5: MONTHLY SPEND BY CATEGORY
C6: Jan | D6: Feb | E6: Mar | F6: Apr | G6: May | H6: Jun | I6: Jul | J6: Aug | K6: Sep | L6: Oct | M6: Nov | N6: Dec | O6: YTD Total
B7: Personnel Costs | C7: 26282 | D7: 27413 | E7: 22840 | F7: 21444 | G7: 23961 | H7: 22396 | I7: 22937 | J7: 22915 | K7: 26218 | L7: 24509 | M7: 25453 | N7: 24175 | O7: =SUM(C7:N7) -> 290543
B8: Recruitment | C8: 28627 | D8: 24977 | E8: 21569 | F8: 22294 | G8: 26734 | H8: 28094 | I8: 22194 | J8: 24700 | K8: 27716 | L8: 25388 | M8: 21380 | N8: 25156 | O8: =SUM(C8:N8) -> 298829
B9: Training & Development | C9: 23415 | D9: 22850 | E9: 28274 | F9: 22042 | G9: 27472 | H9: 26897 | I9: 25696 | J9: 23686 | K9: 21870 | L9: 26265 | M9: 28444 | N9: 22598 | O9: =SUM(C9:N9) -> 299509
B10: Employee Benefits Admin | C10: 22196 | D10: 24813 | E10: 27635 | F10: 21289 | G10: 27166 | H10: 21897 | I10: 21492 | J10: 22348 | K10: 24682 | L10: 28277 | M10: 26209 | N10: 21697 | O10: =SUM(C10:N10) -> 289701
B11: HR Systems | C11: 22387 | D11: 24710 | E11: 21927 | F11: 26262 | G11: 23941 | H11: 28420 | I11: 27397 | J11: 27376 | K11: 23013 | L11: 24484 | M11: 26286 | N11: 21920 | O11: =SUM(C11:N11) -> 298123
B12: Total | C12: =SUM(C7:C11) -> 122907 | D12: =SUM(D7:D11) -> 124763 | E12: =SUM(E7:E11) -> 122245 | F12: =SUM(F7:F11) -> 113331 | G12: =SUM(G7:G11) -> 129274 | H12: =SUM(H7:H11) -> 127704 | I12: =SUM(I7:I11) -> 119716 | J12: =SUM(J7:J11) -> 121025 | ... O12: =SUM(O7:O11) -> 1476705
B14: BUDGET VS ACTUAL
B15: Category | C15: Budget | D15: Actual | E15: Variance | F15: Var % | G15: Status
B16: Personnel Costs | C16: 300000 | D16: =O7 -> 290543 | E16: =D16-C16 -> -9457 | F16: =IF(C16=0,0,(D16-C16)/C16) -> -0.031523333 | G16: ●
B17: Recruitment | C17: 300000 | D17: =O8 -> 298829 | E17: =D17-C17 -> -1171 | F17: =IF(C17=0,0,(D17-C17)/C17) -> -0.0039033333 | G17: ●
B18: Training & Development | C18: 300000 | D18: =O9 -> 299509 | E18: =D18-C18 -> -491 | F18: =IF(C18=0,0,(D18-C18)/C18) -> -0.0016366667 | G18: ●
B19: Employee Benefits Admin | C19: 300000 | D19: =O10 -> 289701 | E19: =D19-C19 -> -10299 | F19: =IF(C19=0,0,(D19-C19)/C19) -> -0.03433 | G19: ●
B20: HR Systems | C20: 300000 | D20: =O11 -> 298123 | E20: =D20-C20 -> -1877 | F20: =IF(C20=0,0,(D20-C20)/C20) -> -0.0062566667 | G20: ●
B21: Total | C21: =SUM(C16:C20) -> 1500000 | D21: =SUM(D16:D20) -> 1476705 | E21: =D21-C21 -> -23295 | F21: =IF(C21=0,0,(D21-C21)/C21) -> -0.01553 | G21: ●
B23: COST CENTER INFORMATION
B24: Manager | C24: James O'Connor
B25: Department | C25: Human Resources
B26: Headcount | C26: 40
B27: Location | C27: Shared Services Center

Sheet CC-3200
B2: CC-3200 - IT & Digital | H2: Cost Center Summary
B3: Cost Center Report
B5: MONTHLY SPEND BY CATEGORY
C6: Jan | D6: Feb | E6: Mar | F6: Apr | G6: May | H6: Jun | I6: Jul | J6: Aug | K6: Sep | L6: Oct | M6: Nov | N6: Dec | O6: YTD Total
B7: Cloud Services | C7: 49750 | D7: 55312 | E7: 56595 | F7: 63353 | G7: 63839 | H7: 50597 | I7: 50713 | J7: 65766 | K7: 54624 | L7: 51772 | M7: 63454 | N7: 93320 | O7: =SUM(C7:N7) -> 719095
B8: Software Licenses | C8: 60165 | D8: 63013 | E8: 64626 | F8: 64513 | G8: 54190 | H8: 56948 | I8: 66811 | J8: 56018 | K8: 60539 | L8: 64397 | M8: 64927 | N8: 900129 | O8: =SUM(C8:N8) -> 1576276
B9: Hardware & Equipment | C9: 55705 | D9: 61662 | E9: 49640 | F9: 55717 | G9: 62863 | H9: 60898 | I9: 50981 | J9: 62176 | K9: 60258 | L9: 57365 | M9: 51414 | N9: 60019 | O9: =SUM(C9:N9) -> 688698
B10: Cybersecurity | C10: 62630 | D10: 53061 | E10: 60694 | F10: 50818 | G10: 53176 | H10: 55853 | I10: 63198 | J10: 54541 | K10: 65163 | L10: 66787 | M10: 52442 | N10: 50050 | O10: =SUM(C10:N10) -> 688413
B11: IT Support Contracts | C11: 62335 | D11: 62959 | E11: 65349 | F11: 61351 | G11: 63235 | H11: 55979 | I11: 51347 | J11: 67081 | K11: 60165 | L11: 54316 | M11: 65206 | N11: 60871 | O11: =SUM(C11:N11) -> 730194
B12: Total | C12: =SUM(C7:C11) -> 290585 | D12: =SUM(D7:D11) -> 296007 | E12: =SUM(E7:E11) -> 296904 | F12: =SUM(F7:F11) -> 295752 | G12: =SUM(G7:G11) -> 297303 | H12: =SUM(H7:H11) -> 280275 | I12: =SUM(I7:I11) -> 283050 | J12: =SUM(J7:J11) -> 305582 | ... O12: =SUM(O7:O11) -> 4402676
B14: BUDGET VS ACTUAL
B15: Category | C15: Budget | D15: Actual | E15: Variance | F15: Var % | G15: Status
B16: Cloud Services | C16: 700000 | D16: =O7 -> 719095 | E16: =D16-C16 -> 19095 | F16: =IF(C16=0,0,(D16-C16)/C16) -> 0.027278571 | G16: ●
B17: Software Licenses | C17: 700000 | D17: =O8 -> 1576276 | E17: =D17-C17 -> 876276 | F17: =IF(C17=0,0,(D17-C17)/C17) -> 1.2518229 | G17: ●
B18: Hardware & Equipment | C18: 700000 | D18: =O9 -> 688698 | E18: =D18-C18 -> -11302 | F18: =IF(C18=0,0,(D18-C18)/C18) -> -0.016145714 | G18: ●
B19: Cybersecurity | C19: 700000 | D19: =O10 -> 688413 | E19: =D19-C19 -> -11587 | F19: =IF(C19=0,0,(D19-C19)/C19) -> -0.016552857 | G19: ●
B20: IT Support Contracts | C20: 700000 | D20: =O11 -> 730194 | E20: =D20-C20 -> 30194 | F20: =IF(C20=0,0,(D20-C20)/C20) -> 0.043134286 | G20: ●
B21: Total | C21: =SUM(C16:C20) -> 3500000 | D21: =SUM(D16:D20) -> 4402676 | E21: =D21-C21 -> 902676 | F21: =IF(C21=0,0,(D21-C21)/C21) -> 0.25790743 | G21: ●
B23: COST CENTER INFORMATION
B24: Manager | C24: Priya Sharma
B25: Department | C25: IT & Digital
B26: Headcount | C26: 95
B27: Location | C27: HQ

Sheet CC-3300
B2: CC-3300 - Legal & Compliance | H2: Cost Center Summary
B3: Cost Center Report
B5: MONTHLY SPEND BY CATEGORY
C6: Jan | D6: Feb | E6: Mar | F6: Apr | G6: May | H6: Jun | I6: Jul | J6: Aug | K6: Sep | L6: Oct | M6: Nov | N6: Dec | O6: YTD Total
B7: Outside Counsel | C7: 20230 | D7: 21617 | E7: 20743 | F7: 22708 | G7: 24180 | H7: 23469 | I7: 23709 | J7: 20668 | K7: 23577 | L7: 26659 | M7: 22141 | N7: 60428 | O7: =SUM(C7:N7) -> 310129
B8: Regulatory Filings | C8: 24299 | D8: 25167 | E8: 24438 | F8: 22909 | G8: 21478 | H8: 20488 | I8: 20626 | J8: 20539 | K8: 25204 | L8: 25694 | M8: 25556 | N8: 26026 | O8: =SUM(C8:N8) -> 282424
B9: Insurance Premiums | C9: 22344 | D9: 24551 | E9: 25575 | F9: 20759 | G9: 19835 | H9: 21300 | I9: 26243 | J9: 25487 | K9: 20740 | L9: 25763 | M9: 21055 | N9: 21700 | O9: =SUM(C9:N9) -> 275352
B10: Contract Management | C10: 21010 | D10: 26020 | E10: 25629 | F10: 20287 | G10: 20000 | H10: 25371 | I10: 22589 | J10: 23812 | K10: 24300 | L10: 23638 | M10: 21149 | N10: 22005 | O10: =SUM(C10:N10) -> 275810
B11: Compliance Training | C11: 24015 | D11: 25323 | E11: 22200 | F11: 19991 | G11: 20850 | H11: 21827 | I11: 26561 | J11: 22822 | K11: 23315 | L11: 22792 | M11: 25896 | N11: 25437 | O11: =SUM(C11:N11) -> 281029
B12: Total | C12: =SUM(C7:C11) -> 111898 | D12: =SUM(D7:D11) -> 122678 | E12: =SUM(E7:E11) -> 118585 | F12: =SUM(F7:F11) -> 106654 | G12: =SUM(G7:G11) -> 106343 | H12: =SUM(H7:H11) -> 112455 | I12: =SUM(I7:I11) -> 119728 | J12: =SUM(J7:J11) -> 113328 | ... O12: =SUM(O7:O11) -> 1424744
B14: BUDGET VS ACTUAL
B15: Category | C15: Budget | D15: Actual | E15: Variance | F15: Var % | G15: Status
B16: Outside Counsel | C16: 280000 | D16: =O7 -> 310129 | E16: =D16-C16 -> 30129 | F16: =IF(C16=0,0,(D16-C16)/C16) -> 0.10760357 | G16: ●
B17: Regulatory Filings | C17: 280000 | D17: =O8 -> 282424 | E17: =D17-C17 -> 2424 | F17: =IF(C17=0,0,(D17-C17)/C17) -> 0.0086571429 | G17: ●
B18: Insurance Premiums | C18: 280000 | D18: =O9 -> 275352 | E18: =D18-C18 -> -4648 | F18: =IF(C18=0,0,(D18-C18)/C18) -> -0.0166 | G18: ●
B19: Contract Management | C19: 280000 | D19: =O10 -> 275810 | E19: =D19-C19 -> -4190 | F19: =IF(C19=0,0,(D19-C19)/C19) -> -0.014964286 | G19: ●
B20: Compliance Training | C20: 280000 | D20: =O11 -> 281029 | E20: =D20-C20 -> 1029 | F20: =IF(C20=0,0,(D20-C20)/C20) -> 0.003675 | G20: ●
B21: Total | C21: =SUM(C16:C20) -> 1400000 | D21: =SUM(D16:D20) -> 1424744 | E21: =D21-C21 -> 24744 | F21: =IF(C21=0,0,(D21-C21)/C21) -> 0.017674286 | G21: ●
B23: COST CENTER INFORMATION
B24: Manager | C24: Thomas Anderson
B25: Department | C25: Legal & Compliance
B26: Headcount | C26: 25
B27: Location | C27: HQ

Sheet CC-4000
B2: CC-4000 - General & Administration | H2: Cost Center Summary
B3: Cost Center Report
B5: MONTHLY SPEND BY CATEGORY
C6: Jan | D6: Feb | E6: Mar | F6: Apr | G6: May | H6: Jun | I6: Jul | J6: Aug | K6: Sep | L6: Oct | M6: Nov | N6: Dec | O6: YTD Total
B7: Executive Compensation | C7: 32860 | D7: 38493 | E7: 37215 | F7: 41039 | G7: 31856 | H7: 37527 | I7: 33254 | J7: 37429 | K7: 40155 | L7: 35940 | M7: 37049 | N7: 35183 | O7: =SUM(C7:N7) -> 438000
B8: Board Expenses | C8: 41559 | D8: 40653 | E8: 32153 | F8: 31636 | G8: 37050 | H8: 34592 | I8: 31510 | J8: 38593 | K8: 32884 | L8: 38248 | M8: 32251 | N8: 39019 | O8: =SUM(C8:N8) -> 430148
B9: Corporate Insurance | C9: 40378 | D9: 39935 | E9: 40879 | F9: 37934 | G9: 34838 | H9: 33173 | I9: 38403 | J9: 41883 | K9: 38405 | L9: 32309 | M9: 31645 | N9: 32841 | O9: =SUM(C9:N9) -> 442623
B10: Professional Services | C10: 39998 | D10: 32661 | E10: 38931 | F10: 37587 | G10: 35179 | H10: 35795 | I10: 34061 | J10: 35687 | K10: 33190 | L10: 36987 | M10: 38435 | N10: 37213 | O10: =SUM(C10:N10) -> 435724
B11: Office Operations | C11: 42071 | D11: 41342 | E11: 40959 | F11: 37809 | G11: 32750 | H11: 39514 | I11: 41545 | J11: 37773 | K11: 36161 | L11: 38374 | M11: 38062 | N11: 40271 | O11: =SUM(C11:N11) -> 466631
B12: Total | C12: =SUM(C7:C11) -> 196866 | D12: =SUM(D7:D11) -> 193084 | E12: =SUM(E7:E11) -> 190137 | F12: =SUM(F7:F11) -> 186005 | G12: =SUM(G7:G11) -> 171673 | H12: =SUM(H7:H11) -> 180601 | I12: =SUM(I7:I11) -> 178773 | J12: =SUM(J7:J11) -> 191365 | ... O12: =SUM(O7:O11) -> 2213126
B14: BUDGET VS ACTUAL
B15: Category | C15: Budget | D15: Actual | E15: Variance | F15: Var % | G15: Status
B16: Executive Compensation | C16: 440000 | D16: =O7 -> 438000 | E16: =D16-C16 -> -2000 | F16: =IF(C16=0,0,(D16-C16)/C16) -> -0.0045454545 | G16: ●
B17: Board Expenses | C17: 440000 | D17: =O8 -> 430148 | E17: =D17-C17 -> -9852 | F17: =IF(C17=0,0,(D17-C17)/C17) -> -0.022390909 | G17: ●
B18: Corporate Insurance | C18: 440000 | D18: =O9 -> 442623 | E18: =D18-C18 -> 2623 | F18: =IF(C18=0,0,(D18-C18)/C18) -> 0.0059613636 | G18: ●
B19: Professional Services | C19: 440000 | D19: =O10 -> 435724 | E19: =D19-C19 -> -4276 | F19: =IF(C19=0,0,(D19-C19)/C19) -> -0.0097181818 | G19: ●
B20: Office Operations | C20: 440000 | D20: =O11 -> 466631 | E20: =D20-C20 -> 26631 | F20: =IF(C20=0,0,(D20-C20)/C20) -> 0.060525 | G20: ●
B21: Total | C21: =SUM(C16:C20) -> 2200000 | D21: =SUM(D16:D20) -> 2213126 | E21: =D21-C21 -> 13126 | F21: =IF(C21=0,0,(D21-C21)/C21) -> 0.0059663636 | G21: ●
B23: COST CENTER INFORMATION
B24: Manager | C24: Elena Petrov
B25: Department | C25: General & Administration
B26: Headcount | C26: 35
B27: Location | C27: HQ

Sheet CC-5000
B2: CC-5000 - Facilities Management | H2: Cost Center Summary
B3: Cost Center Report
B5: MONTHLY SPEND BY CATEGORY
C6: Jan | D6: Feb | E6: Mar | F6: Apr | G6: May | H6: Jun | I6: Jul | J6: Aug | K6: Sep | L6: Oct | M6: Nov | N6: Dec | O6: YTD Total
B7: Rent & Leases | C7: 39752 | D7: 38459 | E7: 43696 | F7: 39584 | G7: 41774 | H7: 37410 | I7: 40462 | J7: 40752 | K7: 41038 | L7: 43433 | M7: 38063 | N7: 36030 | O7: =SUM(C7:N7) -> 480453
B8: Utilities | C8: 38498 | D8: 41031 | E8: 39889 | F8: 38469 | G8: 39056 | H8: 36126 | I8: 35256 | J8: 41887 | K8: 34874 | L8: 40885 | M8: 45703 | N8: 40077 | O8: =SUM(C8:N8) -> 471751
B9: Maintenance & Repairs | C9: 42553 | D9: 43162 | E9: 39857 | F9: 40308 | G9: 36780 | H9: 41525 | I9: 40302 | J9: 38022 | K9: 45253 | L9: 41579 | M9: 38995 | N9: 44831 | O9: =SUM(C9:N9) -> 493167
B10: Security Services | C10: 43161 | D10: 45641 | E10: 38054 | F10: 39770 | G10: 36823 | H10: 42745 | I10: 44087 | J10: 42290 | K10: 42534 | L10: 35724 | M10: 45199 | N10: 35683 | O10: =SUM(C10:N10) -> 491711
B11: Cleaning & Janitorial | C11: 43686 | D11: 36006 | E11: 42230 | F11: 42932 | G11: 36145 | H11: 40697 | I11: 36988 | J11: 45433 | K11: 36191 | L11: 45795 | M11: 40001 | N11: 34062 | O11: =SUM(C11:N11) -> 480166
B12: Total | C12: =SUM(C7:C11) -> 207650 | D12: =SUM(D7:D11) -> 204299 | E12: =SUM(E7:E11) -> 203726 | F12: =SUM(F7:F11) -> 201063 | G12: =SUM(G7:G11) -> 190578 | H12: =SUM(H7:H11) -> 198503 | I12: =SUM(I7:I11) -> 197095 | J12: =SUM(J7:J11) -> 208384 | ... O12: =SUM(O7:O11) -> 2417248
B14: BUDGET VS ACTUAL
B15: Category | C15: Budget | D15: Actual | E15: Variance | F15: Var % | G15: Status
B16: Rent & Leases | C16: 480000 | D16: =O7 -> 480453 | E16: =D16-C16 -> 453 | F16: =IF(C16=0,0,(D16-C16)/C16) -> 0.00094375 | G16: ●
B17: Utilities | C17: 480000 | D17: =O8 -> 471751 | E17: =D17-C17 -> -8249 | F17: =IF(C17=0,0,(D17-C17)/C17) -> -0.017185417 | G17: ●
B18: Maintenance & Repairs | C18: 480000 | D18: =O9 -> 493167 | E18: =D18-C18 -> 13167 | F18: =IF(C18=0,0,(D18-C18)/C18) -> 0.02743125 | G18: ●
B19: Security Services | C19: 480000 | D19: =O10 -> 491711 | E19: =D19-C19 -> 11711 | F19: =IF(C19=0,0,(D19-C19)/C19) -> 0.024397917 | G19: ●
B20: Cleaning & Janitorial | C20: 480000 | D20: =O11 -> 480166 | E20: =D20-C20 -> 166 | F20: =IF(C20=0,0,(D20-C20)/C20) -> 0.00034583333 | G20: ●
B21: Total | C21: =SUM(C16:C20) -> 2400000 | D21: =SUM(D16:D20) -> 2417248 | E21: =D21-C21 -> 17248 | F21: =IF(C21=0,0,(D21-C21)/C21) -> 0.0071866667 | G21: ●
B23: COST CENTER INFORMATION
B24: Manager | C24: Ahmed Hassan
B25: Department | C25: Facilities Management
B26: Headcount | C26: 50
B27: Location | C27: Shared Services Center
